{"eduardo campos":1,"luiz in%C3%A1cio lula da silva":19,"hu jintao":34,"abbas":52,"mahmoud abbas":86,"saddam hussein":94,"tony blair":158,"bush":334,"george w. bush":359,"barack obama":393,"john howard":161,"obama":268,"john mccain":103,"howard":106,"condoleezza rice":116,"gordon brown":130,"hillary clinton":125,"clinton":100,"stephen harper":95,"mahmoud ahmadinejad":100,"brown":89,"david cameron":94,"laura hale":92,"kofi annan":58,"vladimir putin":86,"mccain":59,"smith":70,"blair":74,"ban ki-moon":77,"fernando alonso":82,"nicolas sarkozy":85,"mitt romney":85,"george bush":74,"bill clinton":66,"thaksin shinawatra":69,"christian":67,"felipe massa":69,"lewis hamilton":68,"rico shen":67,"harper":61,"hamid karzai":59,"pervez musharraf":53,"hamilton":58,"day":54,"johnson":56,"kevin rudd":57,"kimi r%C3%A4ikk%C3%B6nen":57,"joe biden":55,"ehud olmert":55,"ron paul":53,"silva":42,"dick cheney":44,"williams":47,"alexander downer":48,"laden":51,"alonso":52,"romney":52}